{"ft": {"https://www.ics.uci.edu/~cbdaviso/ <%split%> Professional Objective: A management position in Information Systems\r\nwith interests in: programming, analysis, database connectivity, operations,\r\nand networking for both telephone systems and computer systems": [2, 597, 0, 0.009852947015207664], "https://www.ics.uci.edu/~dan/genealogy/Krakow/Families/Birkner.html <%split%> Birkner family": [1, 1166, 0, 0.002522388236740555], "https://www.ics.uci.edu/~dan/genealogy/Krakow/Families/Breit.html <%split%> Breit family": [2, 2348, 0, 0.0025051999012261393], "https://www.ics.uci.edu/~dan/genealogy/Krakow/Families/Cypes.html <%split%> Cypes family": [1, 509, 0, 0.005778201736816282], "https://www.ics.uci.edu/~dan/genealogy/Krakow/Families/Etwanig.html <%split%> Etwanig family": [1, 1215, 0, 0.0024206622913905246], "https://www.ics.uci.edu/~dan/genealogy/Krakow/Families/Fischlowicz.html <%split%> Fischlowicz family": [1, 1583, 0, 0.001857930943802582], "https://www.ics.uci.edu/~dan/genealogy/Krakow/Families/Haubenstock.html <%split%> Haubenstock family": [1, 2690, 0, 0.001093347466185683], "https://www.ics.uci.edu/~dan/genealogy/Krakow/Families/Hertzig.html <%split%> Hertzig family": [1, 2045, 0, 0.0014381929995303116], "https://www.ics.uci.edu/~dan/genealogy/Krakow/Families/Kosches.html <%split%> Kosches family": [1, 2000, 0, 0.0014705523420197437], "https://www.ics.uci.edu/~dan/genealogy/Krakow/Families/Pitzele.html <%split%> Pitzele families": [1, 13996, 0, 0.0002101389457015924], "https://www.ics.uci.edu/~dan/genealogy/Krakow/Families/Rubinstein.html <%split%> Rubinstein family": [1, 1747, 0, 0.0016835172776413778], "https://www.ics.uci.edu/~dan/genealogy/Krakow/Families/Silberstein.html <%split%> Silberstein family": [2, 2996, 0, 0.001963354261708603], "https://www.ics.uci.edu/~dan/genealogy/Krakow/Families/Tilles.html <%split%> Tilles family": [22, 2959, 0, 0.02186694932371366], "https://www.ics.uci.edu/~dan/genealogy/Krakow/Families/Zaun.html <%split%> Zaun/Caun/Blaurok family": [2, 2512, 0, 0.0023416438567193374], "https://www.ics.uci.edu/~eppstein/eppstein.html <%split%> Eppstein Relatives and Namesakes": [2, 3414, 0, 0.001722967008810479], "https://www.ics.uci.edu/~gbowker/records.html <%split%> The Multiple Bodies of the Medical \nRecord": [1, 12607, 0, 0.00023329140033628046], "https://www.ics.uci.edu/~ihler/papers/bib.html#wiley_wsn07 <%split%> Alexander Ihler: Publication bibtex": [3, 3747, 0, 0.0023547675612806142], "https://www.ics.uci.edu/~kkask/Spring-2018%20CS273P/Demos/Intro_Tutorial.ipynb <%split%> None": [1, 2148, 0, 0.0013692293687334672], "https://www.ics.uci.edu/~pazzani/Publications/APubs.html <%split%> Michael J. Pazzani: Publications on Machine Learning, KDD and Artificial Intelligence": [1, 3566, 0, 0.0008247629512169062], "https://www.ics.uci.edu/~pazzani/Publications/OldPublications.html#1989 <%split%> Michael Pazzani: Publications on Machine Learning, KDD and Artificial Intelligence": [1, 3943, 0, 0.0007459053218461799], "https://www.ics.uci.edu/~taylor/Publications.htm <%split%> Publications of Richard N. Taylor": [1, 4740, 0, 0.0006204862202614953], "https://www.stat.uci.edu/news/page/4/ <%split%> News": [1, 1147, 0, 0.0025641714769306777]}, "ftable": {"http://flamingo.ics.uci.edu/releases/1.0/src/sepia/cluster/ <%split%> Index of /releases/1.0/src/sepia/cluster": [1, 113, 0, 0.029462697835596185], "http://flamingo.ics.uci.edu/releases/1.0/src/sepia/cluster/cluster.cc <%split%> None": [7, 164, 0, 0.14210362187778405], "http://flamingo.ics.uci.edu/releases/1.0/src/sepia/makefile <%split%> None": [7, 342, 0, 0.06814325727472684], "http://flamingo.ics.uci.edu/releases/1.0/src/sepia/ppdtable/makefile <%split%> None": [5, 194, 0, 0.08580631070676208], "http://flamingo.ics.uci.edu/releases/2.0.1/src/sepia/cluster/ftable.cc <%split%> None": [12, 105, 0, 0.3804896977625564], "http://flamingo.ics.uci.edu/releases/2.0.1/src/sepia/freqest/makefile <%split%> None": [3, 100, 0, 0.09987854566267106], "http://flamingo.ics.uci.edu/releases/2.0.1/src/sepia/ppdtable/makefile <%split%> None": [5, 194, 0, 0.08580631070676208], "http://flamingo.ics.uci.edu/releases/2.0/src/sepia/cluster/ <%split%> Index of /releases/2.0/src/sepia/cluster": [1, 68, 0, 0.048960071403270126], "http://flamingo.ics.uci.edu/releases/4.0/src/sepia/src/cluster/cluster.cc <%split%> None": [7, 164, 0, 0.14210362187778405]}, "ftam": {"https://www.ics.uci.edu/~rohit/IEEE-L7-FTP-COLUMN-FINAL.htm <%split%> I Want My FTP: Bits on Demand": [1, 2196, 0, 0.0019506044466583306]}, "ftc": {"https://www.ics.uci.edu/~feldman/lec19F00.html <%split%> lec19F00.doc": [1, 645, 0, 0.006174414525887926], "https://www.ics.uci.edu/~feldman/lec7F00.html <%split%> lec7F00.doc": [2, 577, 0, 0.013804150326508535]}, "ftcp": {"https://www.ics.uci.edu/~magda/Courses/ics156/old_Lab_4.html <%split%> LABORATORY MANUAL ": [5, 1887, 1, 0.01135009900599283]}, "ftdc": {"https://www.ics.uci.edu/~bic/messengers/ <%split%> Project: MESSENGERS": [4, 2259, 0, 0.007051788170336808], "https://www.ics.uci.edu/~dillenco/pubs/ <%split%> Publications": [3, 1559, 1, 0.007663561326230364]}, "fte": {"https://www.ics.uci.edu/~gbowker/records.html <%split%> The Multiple Bodies of the Medical \nRecord": [2, 12607, 0, 0.0006795474521871491]}, "ftfanout": {"http://flamingo.ics.uci.edu/releases/3.0/src/filtertree/statsutil.cc <%split%> None": [12, 673, 0, 0.07101035427989977], "http://flamingo.ics.uci.edu/releases/4.0/src/filtertree/src/statsutil.cc <%split%> None": [12, 703, 0, 0.06798004044149723]}, "ftfjx": {"https://www.ics.uci.edu/~kay/courses/10a/hw/hw6.html <%split%> ICS 10A Assignment 6 * Fall 2003": [1, 1750, 0, 0.002447729922778111]}, "ftfull": {"https://www.ics.uci.edu/~arcadia/Teamware/docs/AllNames.html <%split%> \n  Index of all Fields and Methods\n": [4, 3718, 1, 0.004284558761912547], "https://www.ics.uci.edu/~arcadia/Teamware/docs/Foundation.Objv.MetaClass.html <%split%> \n  Class Foundation.Objv.MetaClass\n": [6, 550, 1, 0.04344542584579323]}, "ftfulladd": {"https://www.ics.uci.edu/~arcadia/Teamware/docs/AllNames.html <%split%> \n  Index of all Fields and Methods\n": [2, 3718, 1, 0.0021422793809562734], "https://www.ics.uci.edu/~arcadia/Teamware/docs/Foundation.Objv.MetaClass.html <%split%> \n  Class Foundation.Objv.MetaClass\n": [3, 550, 1, 0.021722712922896615]}, "ftfulladdlist": {"https://www.ics.uci.edu/~arcadia/Teamware/docs/AllNames.html <%split%> \n  Index of all Fields and Methods\n": [2, 3718, 1, 0.0021422793809562734], "https://www.ics.uci.edu/~arcadia/Teamware/docs/Foundation.Objv.MetaClass.html <%split%> \n  Class Foundation.Objv.MetaClass\n": [3, 550, 1, 0.021722712922896615]}, "ftfullremove": {"https://www.ics.uci.edu/~arcadia/Teamware/docs/AllNames.html <%split%> \n  Index of all Fields and Methods\n": [2, 3718, 1, 0.0021422793809562734], "https://www.ics.uci.edu/~arcadia/Teamware/docs/Foundation.Objv.MetaClass.html <%split%> \n  Class Foundation.Objv.MetaClass\n": [3, 550, 1, 0.021722712922896615]}, "ftfullremovelist": {"https://www.ics.uci.edu/~arcadia/Teamware/docs/AllNames.html <%split%> \n  Index of all Fields and Methods\n": [2, 3718, 1, 0.0021422793809562734], "https://www.ics.uci.edu/~arcadia/Teamware/docs/Foundation.Objv.MetaClass.html <%split%> \n  Class Foundation.Objv.MetaClass\n": [3, 550, 1, 0.021722712922896615]}, "ftfw": {"https://www.ics.uci.edu/~kkask/Spring-2018%20CS273P/Demos/Intro_Tutorial.ipynb <%split%> None": [1, 2148, 0, 0.00199419337284064]}, "fth": {"https://cbcl.ics.uci.edu/public_data/shilab/forAmber/voila-dnlef/ <%split%> MAJIQ LSV \u0394\u03a8 Summary": [5, 75868, 0, 0.000262462261374869], "https://cbcl.ics.uci.edu/public_data/shilab/forAmber/voila-mock/ <%split%> MAJIQ LSV \u0394\u03a8 Summary": [5, 60135, 0, 0.0003311297388540544]}, "fti": {"http://archive.ics.uci.edu/ml/support/Breast+Cancer#3e78257004181e6dbbdfa3ec12399520412e9c5c <%split%> UCI Machine Learning Repository: Breast Cancer Data Set: Support": [1, 6092, 0, 0.000604311781604355], "http://archive.ics.uci.edu/ml/support/Breast+Cancer+Wisconsin+(Diagnostic)#93e4d326f6a322d66e034c1b88773f3a7f621526 <%split%> UCI Machine Learning Repository: Breast Cancer Wisconsin (Diagnostic) Data Set: Support": [1, 2801, 0, 0.0013143403689874085], "http://archive.ics.uci.edu/ml/support/Breast+Cancer+Wisconsin+(Original)#ac8fe867e1d16d4d09f9bd759ba46699055c7ca6 <%split%> UCI Machine Learning Repository: Breast Cancer Wisconsin (Original) Data Set: Support": [1, 2801, 0, 0.0013143403689874085], "http://archive.ics.uci.edu/ml/support/Thyroid+Disease#076c5b4e7bf69148bcde8c83621ecf1140a7d55c <%split%> UCI Machine Learning Repository: Thyroid Disease Data Set: Support": [2, 1799, 0, 0.004092793077858511]}, "ftime": {"http://sli.ics.uci.edu/PmWiki/BasicVariables <%split%> SLI | PmWiki / BasicVariables ": [1, 1342, 0, 0.0026710561553842586], "http://sli.ics.uci.edu/PmWiki/ChangeLog <%split%> SLI | PmWiki / ChangeLog ": [3, 5996, 0, 0.0017934743298160484], "http://sli.ics.uci.edu/PmWiki/MarkupExpressions <%split%> SLI | PmWiki / MarkupExpressions ": [16, 788, 1, 0.07278289056904923], "http://sli.ics.uci.edu/pmwiki/pmwiki.php?n=PmWiki%2FPageLists#includevariable <%split%> SLI | PmWiki / PageLists ": [1, 2791, 0, 0.0012843272520693925], "http://sli.ics.uci.edu/pmwiki/pmwiki.php?n=PmWiki%2FPageTextVariables#pagelists <%split%> SLI | PmWiki / PageTextVariables ": [1, 1000, 0, 0.003584557360525675]}, "ftimefmt": {"http://sli.ics.uci.edu/PmWiki/BasicVariables <%split%> SLI | PmWiki / BasicVariables ": [2, 1342, 0, 0.005486538559662788], "http://sli.ics.uci.edu/PmWiki/ChangeLog <%split%> SLI | PmWiki / ChangeLog ": [1, 5996, 0, 0.0006139872204025569], "http://sli.ics.uci.edu/PmWiki/MarkupExpressions <%split%> SLI | PmWiki / MarkupExpressions ": [2, 788, 0, 0.009343825821151602], "http://sli.ics.uci.edu/PmWiki/Variables <%split%> SLI | PmWiki / Variables ": [1, 813, 0, 0.004528250151948009]}, "ftindexerab": {"http://flamingo.ics.uci.edu/releases/2.0.1/src/filtertree/ <%split%> Index of /releases/2.0.1/src/filtertree": [1, 37, 0, 0.09473989498589325], "http://flamingo.ics.uci.edu/releases/2.0/src/filtertree/ <%split%> Index of /releases/2.0/src/filtertree": [1, 76, 0, 0.04612336992734276], "http://flamingo.ics.uci.edu/releases/2.0/src/filtertree/ftindexerabs.cc <%split%> None": [1, 1, 0, 3.50537611447805], "http://flamingo.ics.uci.edu/releases/2.0/src/filtertree/makefile <%split%> None": [5, 240, 0, 0.07302866905162604], "http://flamingo.ics.uci.edu/releases/3.0/src/filtertree/ <%split%> Index of /releases/3.0/src/filtertree": [1, 43, 0, 0.08152037475530349], "http://flamingo.ics.uci.edu/releases/4.0/src/filtertree/src/ <%split%> Index of /releases/4.0/src/filtertree/src": [1, 43, 0, 0.08152037475530349]}, "ftindexercombinelist": {"http://flamingo.ics.uci.edu/releases/3.0/src/filtertree/ <%split%> Index of /releases/3.0/src/filtertree": [1, 43, 0, 0.08152037475530349], "http://flamingo.ics.uci.edu/releases/3.0/src/filtertree/example.cc <%split%> None": [1, 1527, 0, 0.002295596669599247], "http://flamingo.ics.uci.edu/releases/4.0/src/filtertree/src/ <%split%> Index of /releases/4.0/src/filtertree/src": [1, 43, 0, 0.08152037475530349], "http://flamingo.ics.uci.edu/releases/4.0/src/filtertree/src/example.cc <%split%> None": [1, 2074, 0, 0.0016901524177811236], "http://flamingo.ics.uci.edu/releases/4.1/src/filtertree/src/example.cc <%split%> None": [1, 2251, 0, 0.0015572528274002888], "http://flamingo.ics.uci.edu/releases/4.1/src/filtertree/src/ftindexercombinelists.cc <%split%> None": [1, 3, 0, 1.1684587048260167]}, "ftindexercombinelistsbasic": {"http://flamingo.ics.uci.edu/releases/3.0/src/filtertree/example.cc <%split%> None": [2, 1527, 0, 0.004591193339198494], "http://flamingo.ics.uci.edu/releases/3.0/src/filtertree/perftest.cc <%split%> None": [2, 1159, 0, 0.006048966547848231], "http://flamingo.ics.uci.edu/releases/4.0/src/filtertree/src/example.cc <%split%> None": [2, 2074, 0, 0.003380304835562247], "http://flamingo.ics.uci.edu/releases/4.0/src/filtertree/src/perftest.cc <%split%> None": [2, 1303, 0, 0.005380469861056101], "http://flamingo.ics.uci.edu/releases/4.1/src/filtertree/src/example.cc <%split%> None": [2, 2251, 0, 0.0031145056548005775], "http://flamingo.ics.uci.edu/releases/4.1/src/filtertree/src/unittest.cc <%split%> None": [16, 3262, 0, 0.01719375163447235]}, "ftindexercombinelistscost": {"http://flamingo.ics.uci.edu/releases/3.0/src/filtertree/example.cc <%split%> None": [5, 1527, 0, 0.011477983347996235], "http://flamingo.ics.uci.edu/releases/3.0/src/filtertree/perftest.cc <%split%> None": [2, 1159, 0, 0.006048966547848231], "http://flamingo.ics.uci.edu/releases/4.0/src/filtertree/src/example.cc <%split%> None": [5, 2074, 0, 0.008450762088905618], "http://flamingo.ics.uci.edu/releases/4.0/src/filtertree/src/perftest.cc <%split%> None": [2, 1303, 0, 0.005380469861056101], "http://flamingo.ics.uci.edu/releases/4.1/src/filtertree/src/example.cc <%split%> None": [5, 2251, 0, 0.007786264137001444], "http://flamingo.ics.uci.edu/releases/4.1/src/filtertree/src/unittest.cc <%split%> None": [16, 3262, 0, 0.01719375163447235]}, "ftindexerdiscardlist": {"http://flamingo.ics.uci.edu/releases/3.0/src/filtertree/ <%split%> Index of /releases/3.0/src/filtertree": [1, 43, 0, 0.08336179908199244], "http://flamingo.ics.uci.edu/releases/3.0/src/filtertree/example.cc <%split%> None": [1, 1527, 0, 0.002347450792747659], "http://flamingo.ics.uci.edu/releases/4.0/src/filtertree/src/ <%split%> Index of /releases/4.0/src/filtertree/src": [1, 43, 0, 0.08336179908199244], "http://flamingo.ics.uci.edu/releases/4.0/src/filtertree/src/example.cc <%split%> None": [1, 2074, 0, 0.001728330453483932], "http://flamingo.ics.uci.edu/releases/4.1/src/filtertree/src/example.cc <%split%> None": [1, 2251, 0, 0.001592428858518736]}, "ftindexerdiscardlistsllf": {"http://flamingo.ics.uci.edu/releases/3.0/src/filtertree/example.cc <%split%> None": [2, 1527, 0, 0.004591193339198494], "http://flamingo.ics.uci.edu/releases/3.0/src/filtertree/perftest.cc <%split%> None": [2, 1159, 0, 0.006048966547848231], "http://flamingo.ics.uci.edu/releases/4.0/src/filtertree/src/example.cc <%split%> None": [2, 2074, 0, 0.003380304835562247], "http://flamingo.ics.uci.edu/releases/4.0/src/filtertree/src/perftest.cc <%split%> None": [2, 1303, 0, 0.005380469861056101], "http://flamingo.ics.uci.edu/releases/4.1/src/filtertree/src/example.cc <%split%> None": [2, 2251, 0, 0.0031145056548005775], "http://flamingo.ics.uci.edu/releases/4.1/src/filtertree/src/unittest.cc <%split%> None": [16, 3262, 0, 0.01719375163447235]}, "ftindexerdiscardlistspaniccost": {"http://flamingo.ics.uci.edu/releases/3.0/src/filtertree/example.cc <%split%> None": [2, 1527, 0, 0.004591193339198494], "http://flamingo.ics.uci.edu/releases/3.0/src/filtertree/perftest.cc <%split%> None": [2, 1159, 0, 0.006048966547848231], "http://flamingo.ics.uci.edu/releases/4.0/src/filtertree/src/example.cc <%split%> None": [2, 2074, 0, 0.003380304835562247], "http://flamingo.ics.uci.edu/releases/4.0/src/filtertree/src/perftest.cc <%split%> None": [2, 1303, 0, 0.005380469861056101], "http://flamingo.ics.uci.edu/releases/4.1/src/filtertree/src/example.cc <%split%> None": [2, 2251, 0, 0.0031145056548005775], "http://flamingo.ics.uci.edu/releases/4.1/src/filtertree/src/unittest.cc <%split%> None": [22, 3262, 0, 0.02364140849739948]}, "ftindexerdiscardlistspaniccostplus": {"http://flamingo.ics.uci.edu/releases/4.1/src/filtertree/src/unittest.cc <%split%> None": [10, 3262, 0, 0.013131598298165832]}, "ftindexerdiscardlistsrandom": {"http://flamingo.ics.uci.edu/releases/3.0/src/filtertree/example.cc <%split%> None": [2, 1527, 0, 0.004591193339198494], "http://flamingo.ics.uci.edu/releases/3.0/src/filtertree/perftest.cc <%split%> None": [2, 1159, 0, 0.006048966547848231], "http://flamingo.ics.uci.edu/releases/4.0/src/filtertree/src/example.cc <%split%> None": [2, 2074, 0, 0.003380304835562247], "http://flamingo.ics.uci.edu/releases/4.0/src/filtertree/src/perftest.cc <%split%> None": [2, 1303, 0, 0.005380469861056101], "http://flamingo.ics.uci.edu/releases/4.1/src/filtertree/src/example.cc <%split%> None": [2, 2251, 0, 0.0031145056548005775], "http://flamingo.ics.uci.edu/releases/4.1/src/filtertree/src/unittest.cc <%split%> None": [16, 3262, 0, 0.01719375163447235]}, "ftindexerdiscardlistsslf": {"http://flamingo.ics.uci.edu/releases/3.0/src/filtertree/example.cc <%split%> None": [2, 1527, 0, 0.004591193339198494], "http://flamingo.ics.uci.edu/releases/3.0/src/filtertree/perftest.cc <%split%> None": [2, 1159, 0, 0.006048966547848231], "http://flamingo.ics.uci.edu/releases/4.0/src/filtertree/src/example.cc <%split%> None": [2, 2074, 0, 0.003380304835562247], "http://flamingo.ics.uci.edu/releases/4.0/src/filtertree/src/perftest.cc <%split%> None": [2, 1303, 0, 0.005380469861056101], "http://flamingo.ics.uci.edu/releases/4.1/src/filtertree/src/example.cc <%split%> None": [2, 2251, 0, 0.0031145056548005775], "http://flamingo.ics.uci.edu/releases/4.1/src/filtertree/src/unittest.cc <%split%> None": [16, 3262, 0, 0.01719375163447235]}, "ftindexerdiscardliststimecost": {"http://flamingo.ics.uci.edu/releases/3.0/src/filtertree/example.cc <%split%> None": [6, 1527, 0, 0.013773580017595481], "http://flamingo.ics.uci.edu/releases/3.0/src/filtertree/perftest.cc <%split%> None": [2, 1159, 0, 0.006048966547848231], "http://flamingo.ics.uci.edu/releases/4.0/src/filtertree/src/example.cc <%split%> None": [6, 2074, 0, 0.010140914506686742], "http://flamingo.ics.uci.edu/releases/4.0/src/filtertree/src/perftest.cc <%split%> None": [2, 1303, 0, 0.005380469861056101], "http://flamingo.ics.uci.edu/releases/4.1/src/filtertree/src/example.cc <%split%> None": [6, 2251, 0, 0.009343516964401733], "http://flamingo.ics.uci.edu/releases/4.1/src/filtertree/src/unittest.cc <%split%> None": [22, 3262, 0, 0.02364140849739948]}, "ftindexerdiscardliststimecostplus": {"http://flamingo.ics.uci.edu/releases/4.1/src/filtertree/src/unittest.cc <%split%> None": [10, 3262, 0, 0.013131598298165832]}, "ftindexerholesgloballlf": {"http://flamingo.ics.uci.edu/releases/3.0/src/filtertree/unittest.cc <%split%> None": [16, 3289, 0, 0.020838077785888448]}, "ftindexerholesglobalpaniccost": {"http://flamingo.ics.uci.edu/releases/3.0/src/filtertree/unittest.cc <%split%> None": [22, 3289, 0, 0.028652356955596616]}, "ftindexerholesglobalpaniccostplus": {"http://flamingo.ics.uci.edu/releases/3.0/src/filtertree/unittest.cc <%split%> None": [10, 3289, 0, 0.013023798616180278]}, "ftindexerholesglobalrandom": {"http://flamingo.ics.uci.edu/releases/3.0/src/filtertree/unittest.cc <%split%> None": [16, 3289, 0, 0.020838077785888448]}, "ftindexerholesglobalslf": {"http://flamingo.ics.uci.edu/releases/3.0/src/filtertree/unittest.cc <%split%> None": [16, 3289, 0, 0.020838077785888448]}, "ftindexerholesglobaltimecost": {"http://flamingo.ics.uci.edu/releases/3.0/src/filtertree/unittest.cc <%split%> None": [22, 3289, 0, 0.028652356955596616]}, "ftindexerholesglobaltimecostplus": {"http://flamingo.ics.uci.edu/releases/3.0/src/filtertree/unittest.cc <%split%> None": [10, 3289, 0, 0.013023798616180278]}, "ftindexermem": {"http://flamingo.ics.uci.edu/releases/3.0/src/filtertree/ <%split%> Index of /releases/3.0/src/filtertree": [1, 43, 0, 0.07636110150841148], "http://flamingo.ics.uci.edu/releases/3.0/src/filtertree/example.cc <%split%> None": [7, 1527, 0, 0.015052188313052951], "http://flamingo.ics.uci.edu/releases/3.0/src/filtertree/perftest.cc <%split%> None": [1, 1159, 0, 0.0028330693398288987], "http://flamingo.ics.uci.edu/releases/3.0/src/filtertree/unittest.cc <%split%> None": [17, 3289, 0, 0.01697171334832739], "http://flamingo.ics.uci.edu/releases/4.0/src/filtertree/src/ <%split%> Index of /releases/4.0/src/filtertree/src": [1, 43, 0, 0.07636110150841148], "http://flamingo.ics.uci.edu/releases/4.0/src/filtertree/src/example.cc <%split%> None": [10, 2074, 0, 0.015831858075514436], "http://flamingo.ics.uci.edu/releases/4.0/src/filtertree/src/ftindexermem.cc <%split%> None": [1, 1, 0, 3.2835273648616936], "http://flamingo.ics.uci.edu/releases/4.0/src/filtertree/src/perftest.cc <%split%> None": [6, 1303, 0, 0.015119849723077639], "http://flamingo.ics.uci.edu/releases/4.1/src/filtertree/src/example.cc <%split%> None": [12, 2251, 0, 0.017504366227605653], "http://flamingo.ics.uci.edu/releases/4.1/src/filtertree/src/unittest.cc <%split%> None": [17, 3262, 0, 0.017112190436127772]}, "ftindexermemab": {"http://flamingo.ics.uci.edu/releases/2.0.1/src/filtertree/ <%split%> Index of /releases/2.0.1/src/filtertree": [1, 37, 0, 0.09687992866285608], "http://flamingo.ics.uci.edu/releases/2.0/src/filtertree/ <%split%> Index of /releases/2.0/src/filtertree": [1, 76, 0, 0.047165228427969406], "http://flamingo.ics.uci.edu/releases/2.0/src/filtertree/makefile <%split%> None": [5, 240, 0, 0.07467827834428489], "http://flamingo.ics.uci.edu/releases/3.0/src/filtertree/ <%split%> Index of /releases/3.0/src/filtertree": [1, 43, 0, 0.08336179908199244], "http://flamingo.ics.uci.edu/releases/4.0/src/filtertree/src/ <%split%> Index of /releases/4.0/src/filtertree/src": [1, 43, 0, 0.08336179908199244]}, "ftindexerondisk": {"http://flamingo.ics.uci.edu/releases/3.0/src/filtertree/ <%split%> Index of /releases/3.0/src/filtertree": [1, 43, 0, 0.07861482274115697], "http://flamingo.ics.uci.edu/releases/3.0/src/filtertree/example.cc <%split%> None": [5, 1527, 0, 0.011068884668859691], "http://flamingo.ics.uci.edu/releases/3.0/src/filtertree/perftest.cc <%split%> None": [3, 1159, 0, 0.008750053609671482], "http://flamingo.ics.uci.edu/releases/4.0/src/filtertree/src/ <%split%> Index of /releases/4.0/src/filtertree/src": [1, 43, 0, 0.07861482274115697], "http://flamingo.ics.uci.edu/releases/4.0/src/filtertree/src/example.cc <%split%> None": [5, 2074, 0, 0.008149559734497951], "http://flamingo.ics.uci.edu/releases/4.0/src/filtertree/src/ftindexerondisk.cc <%split%> None": [1, 1, 0, 3.38043737786975], "http://flamingo.ics.uci.edu/releases/4.0/src/filtertree/src/perftest.cc <%split%> None": [1, 1303, 0, 0.002594349484167114], "http://flamingo.ics.uci.edu/releases/4.1/src/filtertree/src/example.cc <%split%> None": [5, 2251, 0, 0.007508745841558751]}, "ftindexersimple": {"http://flamingo.ics.uci.edu/releases/2.0.1/src/filtertree/ <%split%> Index of /releases/2.0.1/src/filtertree": [1, 37, 0, 0.09136317237485811], "http://flamingo.ics.uci.edu/releases/2.0.1/src/filtertree/unittest.cc <%split%> None": [17, 510, 0, 0.11268124592899166], "http://flamingo.ics.uci.edu/releases/2.0.1/src/filtertree/wrappers/makefile <%split%> None": [1, 111, 0, 0.03045439079161937], "http://flamingo.ics.uci.edu/releases/2.0/src/filtertree/ <%split%> Index of /releases/2.0/src/filtertree": [1, 76, 0, 0.04447943918249671], "http://flamingo.ics.uci.edu/releases/2.0/src/filtertree/example.cc <%split%> None": [6, 554, 0, 0.03661123513938357], "http://flamingo.ics.uci.edu/releases/2.0/src/filtertree/ftindexersimple.cc <%split%> None": [1, 1, 0, 3.38043737786975], "http://flamingo.ics.uci.edu/releases/2.0/src/filtertree/makefile <%split%> None": [7, 240, 0, 0.0985960901878677], "http://flamingo.ics.uci.edu/releases/2.0/src/filtertree/perftest.cc <%split%> None": [2, 208, 0, 0.0325042055564399]}, "ftindexerunionglobalbasic": {"http://flamingo.ics.uci.edu/releases/3.0/src/filtertree/unittest.cc <%split%> None": [16, 3289, 0, 0.020838077785888448]}, "ftindexerunionglobalcost": {"http://flamingo.ics.uci.edu/releases/3.0/src/filtertree/unittest.cc <%split%> None": [16, 3289, 0, 0.020838077785888448]}, "ftkge": {"https://www.ics.uci.edu/~kkask/Spring-2018%20CS273P/Demos/Intro_Tutorial.ipynb <%split%> None": [1, 2148, 0, 0.00199419337284064]}, "ftl": {"https://cbcl.ics.uci.edu/public_data/shilab/forColleen/MAJIQ/voila-KO-cort/ <%split%> MAJIQ LSV \u0394\u03a8 Summary": [4, 44533, 0, 0.0003306731972724704], "https://cbcl.ics.uci.edu/public_data/shilab/forColleen/MAJIQ/voila-KO-hind/ <%split%> MAJIQ LSV \u0394\u03a8 Summary": [4, 215444, 0, 6.83512629459856e-05], "https://cbcl.ics.uci.edu/public_data/shilab/forColleen/MAJIQ/voila-Wt-cort/ <%split%> MAJIQ LSV \u0394\u03a8 Summary": [4, 185124, 0, 7.954597725921504e-05], "https://cbcl.ics.uci.edu/public_data/shilab/forColleen/MAJIQ/voila-Wt-hind/ <%split%> MAJIQ LSV \u0394\u03a8 Summary": [4, 212660, 0, 6.924607116587476e-05]}, "ftm": {"https://www.ics.uci.edu/~dan/genealogy/Miller/langsam/estrlang.htm <%split%> The Esther Jacobs nee Langsam Family": [1, 2638, 0, 0.0014429136126391322], "https://www.ics.uci.edu/~dan/genealogy/Miller/spira/kalich.htm <%split%> The Frieda Kallech nee Uri Family": [1, 3397, 0, 0.0011205199028972714], "https://www.ics.uci.edu/~dan/genealogy/Miller/spira/polimer.htm <%split%> The Henya Polimer nee Uri Family": [2, 2832, 0, 0.002688139908292395]}, "fto": {"https://cbcl.ics.uci.edu/public_data/shilab/forColleen/MAJIQ/voila-KO-cort/ <%split%> MAJIQ LSV \u0394\u03a8 Summary": [2, 44533, 0, 0.0001653365986362352], "https://cbcl.ics.uci.edu/public_data/shilab/forColleen/MAJIQ/voila-KO-hind/ <%split%> MAJIQ LSV \u0394\u03a8 Summary": [2, 215444, 0, 3.41756314729928e-05], "https://cbcl.ics.uci.edu/public_data/shilab/forColleen/MAJIQ/voila-Wt-cort/ <%split%> MAJIQ LSV \u0394\u03a8 Summary": [2, 185124, 0, 3.977298862960752e-05], "https://cbcl.ics.uci.edu/public_data/shilab/forColleen/MAJIQ/voila-Wt-hind/ <%split%> MAJIQ LSV \u0394\u03a8 Summary": [2, 212660, 0, 3.462303558293738e-05]}, "ftoff": {"https://www.ics.uci.edu/~arcadia/Teamware/docs/AllNames.html <%split%> \n  Index of all Fields and Methods\n": [2, 3718, 1, 0.0021422793809562734], "https://www.ics.uci.edu/~arcadia/Teamware/docs/Foundation.Objv.MetaClass.html <%split%> \n  Class Foundation.Objv.MetaClass\n": [3, 550, 1, 0.021722712922896615]}, "fton": {"https://www.ics.uci.edu/~arcadia/Teamware/docs/AllNames.html <%split%> \n  Index of all Fields and Methods\n": [2, 3718, 1, 0.0021422793809562734], "https://www.ics.uci.edu/~arcadia/Teamware/docs/Foundation.Objv.MetaClass.html <%split%> \n  Class Foundation.Objv.MetaClass\n": [3, 550, 1, 0.021722712922896615]}, "ftozom": {"https://www.ics.uci.edu/~eppstein/junkyard/polyomino-inclusion.html <%split%> None": [1, 2247, 0, 0.0019063317155592764]}, "ftp": {"https://www.ics.uci.edu/~arcadia/system_pages/amadeus.html <%split%>  Amadeus": [1, 361, 0, 0.00672076140839453], "https://www.ics.uci.edu/~arcadia/system_pages/apt.html <%split%>  APT": [2, 360, 0, 0.013478860380169029], "https://www.ics.uci.edu/~arcadia/system_pages/cats_pal.html <%split%>  CATS/Pal": [2, 774, 0, 0.00626923738612513], "https://www.ics.uci.edu/~asuncion/personalblog/blog.htm <%split%> Arthur Asuncion's Official Site: Blog": [1, 685, 0, 0.0035418903188765326], "https://www.ics.uci.edu/~cbdaviso/net-status/ <%split%> HostMonitor report": [1, 259, 0, 0.009367547754557627], "https://www.ics.uci.edu/~dan/class/267P/datasets/calgary/news <%split%> None": [3, 42135, 0, 0.00017274438365471164], "https://www.ics.uci.edu/~dan/class/267P/rfc2301/chapter11.html#T.44 <%split%> Zvon - RFC 2301 - References": [3, 250, 0, 0.029114338421165103], "https://www.ics.uci.edu/~ejw/authoring/collection/redirect-issues.html <%split%> Redirect References: Last Call Issues": [1, 3223, 0, 0.00075277532374509], "https://www.ics.uci.edu/~ejw/authoring/dist-auth-tools.html <%split%> Distributed Web Content Authoring Tools": [1, 470, 0, 0.00516211674134133], "https://www.ics.uci.edu/~ejw/authoring/mime-res/draft-stracke-webdav-mime-resource-00.txt <%split%> Sweetgrass & City Streets": [4, 1059, 0, 0.00916409770889679], "https://www.ics.uci.edu/~ejw/authoring/proposals/metadata.html <%split%> A Proposal for Web Metadata Operations": [2, 3237, 0, 0.0014990391525674545], "https://www.ics.uci.edu/~ejw/authoring/protocol/draft-ietf-webdav-protocol-00.txt <%split%> Hello world HTML page": [1, 16023, 0, 0.00015141951372592058], "https://www.ics.uci.edu/~ejw/authoring/protocol/draft-ietf-webdav-protocol-01.txt <%split%> Hello world HTML page": [1, 16053, 0, 0.00015113653948984148], "https://www.ics.uci.edu/~ejw/authoring/protocol/draft-ietf-webdav-protocol-03.html <%split%>  Extensions for Distributed Authoring and Versioning\r\n                              on the\r\n                      World Wide Web -- WEBDAV\r\n": [2, 15248, 0, 0.00031823122618447337], "https://www.ics.uci.edu/~ejw/authoring/protocol/draft-ietf-webdav-protocol-06.html <%split%>   Extensions for Distributed Authoring on the World Wide Web -- WEBDAV": [2, 19610, 0, 0.00024744465766755994], "https://www.ics.uci.edu/~ejw/authoring/protocol/draft-ietf-webdav-protocol-06.txt <%split%> None": [2, 19860, 0, 0.00024432979541091893], "https://www.ics.uci.edu/~ejw/authoring/protocol/draft-ietf-webdav-protocol-07.txt <%split%> None": [3, 20525, 0, 0.0003546204436195506], "https://www.ics.uci.edu/~ejw/authoring/protocol/draft-ietf-webdav-protocol-08.txt <%split%> None": [3, 21066, 0, 0.0003455133677628062], "https://www.ics.uci.edu/~ejw/authoring/protocol/draft-ietf-webdav-protocol-09.txt <%split%> Frobnostication": [2, 23063, 0, 0.00021039716155143954], "https://www.ics.uci.edu/~ejw/authoring/protocol/rfc2518.fr.html <%split%> RFC 2518": [2, 20703, 0, 0.00023438099487324785], "https://www.ics.uci.edu/~ejw/authoring/protocol/rfc2518.html <%split%> HTTP Extensions for Distributed Authoring -- WEBDAV": [2, 21979, 0, 0.0002207739085882365], "https://www.ics.uci.edu/~ejw/authoring/protocol/rfc2518.xml <%split%> HTTP Extensions for Distributed Authoring -- WEBDAV": [2, 20877, 0, 0.00023242753924705896], "https://www.ics.uci.edu/~ejw/authoring/requirements/draft-ietf-webdav-requirements-01.txt <%split%> None": [1, 5126, 0, 0.00047331152329895145], "https://www.ics.uci.edu/~ejw/authoring/requirements/draft-ietf-webdav-requirements-02.txt <%split%> None": [1, 5287, 0, 0.00045889821608292516], "https://www.ics.uci.edu/~ejw/authoring/requirements/draft-ietf-webdav-requirements-03.html <%split%> WebDAV Requirements": [1, 5155, 0, 0.00047064885905536856], "https://www.ics.uci.edu/~ejw/authoring/requirements/draft-ietf-webdav-requirements-03.txt <%split%> None": [1, 5280, 0, 0.0004595066038693987], "https://www.ics.uci.edu/~ejw/authoring/requirements/draft-whitehead-http-distreq-00.html <%split%> Requirements for Distributed Editing": [1, 2958, 0, 0.0008202146275964926], "https://www.ics.uci.edu/~ejw/authoring/requirements/webdav-req-021097.txt <%split%> None": [2, 5202, 0, 0.0009327931058940504], "https://www.ics.uci.edu/~ejw/authoring/sanmateo/Minutes_afternoon.html <%split%> Detailed Minutes of San Mateo Distributed Authoring Meeting (Afternoon)\n": [4, 3552, 0, 0.002732201428412641], "https://www.ics.uci.edu/~ejw/authoring/webdav-req-00.html <%split%> Untitled": [1, 5722, 0, 0.00042401168619895575], "https://www.ics.uci.edu/~ejw/authoring/webdav-req-00.txt <%split%> None": [1, 5744, 0, 0.00042238768600808235], "https://www.ics.uci.edu/~ejw/versioning/ <%split%> WWW Configuration Management Home Page": [1, 2052, 0, 0.0011823561736990374], "https://www.ics.uci.edu/~ejw/versioning/arch/0059.html <%split%> Archive of Working Group on Versioning and Configuration Management of World Wide Web Content: Re: Version identifier in URL": [4, 486, 0, 0.019968682044694857], "https://www.ics.uci.edu/~ejw/versioning/arch/0096.html <%split%> Archive of Working Group on Versioning and Configuration Management of World Wide Web Content: Draft functional requirements (strawman or woodman, you decide!)": [1, 1816, 0, 0.0013360103901048598], "https://www.ics.uci.edu/~eppstein/bibs/eppstein.html <%split%> BibTeX: David Eppstein": [3, 14330, 0, 0.0005079263506832712], "https://www.ics.uci.edu/~eppstein/bibs/kpath.bib <%split%> None": [1, 17189, 0, 0.00014114811032814154], "https://www.ics.uci.edu/~eppstein/gina/dt-interpolate.html <%split%> Geometry in Action": [1, 632, 0, 0.0038389159310607992], "https://www.ics.uci.edu/~eppstein/junkyard/all.html <%split%> The Geometry Junkyard: All Topics": [1, 21271, 0, 0.00011406115690049481], "https://www.ics.uci.edu/~eppstein/junkyard/hedronometry.html <%split%> None": [1, 5250, 0, 0.00046213235589150954], "https://www.ics.uci.edu/~fielding/pubs/dissertation/evaluation.htm <%split%> Fielding Dissertation: CHAPTER 6: Experience and Evaluation": [2, 10412, 0, 0.0004660381998521754], "https://www.ics.uci.edu/~fielding/pubs/dissertation/net_arch_styles.htm <%split%> \nFielding Dissertation: CHAPTER 3: Network-based Architectural Styles\n": [1, 5927, 0, 0.00040934619005068753], "https://www.ics.uci.edu/~fielding/pubs/dissertation/rest_arch_style.htm <%split%> \nFielding Dissertation: CHAPTER 5: Representational State Transfer (REST)\n": [1, 6522, 0, 0.00037200166642600813], "https://www.ics.uci.edu/~gbowker/classification/ <%split%> WORKING INFRASTRUCTURES:": [1, 33289, 0, 7.288278015051293e-05], "https://www.ics.uci.edu/~goodrich/pubs/io.html <%split%> ACM Computing Surveys: SDCR Working Group on Storage I/O, \nCormen/Goodrich": [1, 1202, 0, 0.002018464948777392], "https://www.ics.uci.edu/~ics1c/doc/guide.61.html/guide.12.html <%split%> Guide to Cyberspace 6.1: How can I get more information?": [15, 839, 0, 0.0433765471113902], "https://www.ics.uci.edu/~ics1c/doc/guide.61.html/guide.15.html <%split%> Guide to Cyberspace 6.1: Index/Glossary": [2, 773, 1, 0.006277347654412484], "https://www.ics.uci.edu/~ics1c/doc/spiders.html <%split%> New Spiders Roam the Web": [1, 1020, 0, 0.0023786224200298286], "https://www.ics.uci.edu/~ics1c/doc/urls.html <%split%> URLs, Uniform Resource Locators": [1, 205, 0, 0.011835096919172805], "https://www.ics.uci.edu/~ics1c/hw3/07.html <%split%> ICS 1C HW 3 for Hung T. Tran": [2, 1255, 0, 0.003866446005466813], "https://www.ics.uci.edu/~ics1c/hw3/30.html <%split%> ICS 1C HW 2 for QQ Skeleton -- Title": [1, 801, 0, 0.003028957388802029], "https://www.ics.uci.edu/~ics1c/hw3/35.html <%split%> Chris Yellen's WEB page": [1, 979, 0, 0.0024782378635652964], "https://www.ics.uci.edu/~ics1c/hw4/08.html <%split%> Intel's Pentium Chip Flaw": [1, 2050, 0, 0.0011835096919172805], "https://www.ics.uci.edu/~ics1c/hw4/19.html <%split%> ICS 1C HW 4 for QQ Skeleton -- Title": [2, 1621, 0, 0.0029934544952873844], "https://www.ics.uci.edu/~ics1c/hw4/25.html <%split%> ICS 1C HW 4 Proposals": [1, 1497, 0, 0.001620704654930144], "https://www.ics.uci.edu/~ics1c/hw4/35.html <%split%> The Virtual Classroom: Education on the Internet": [5, 2726, 1, 0.004450100639087354], "https://www.ics.uci.edu/~irus/wisen/twist99/presentations/fielding/fielding-qna.html <%split%> TWIST'99 - Roy Fielding - Q & A": [2, 602, 0, 0.008060448067875167], "https://www.ics.uci.edu/~irus/wisen/wisen98/presentations/Isaacson/tsld004.htm <%split%> Internet Printing Protocol (IPP) IETF Working Group": [1, 49, 0, 0.04951418098837602], "https://www.ics.uci.edu/~kay/courses/10/topics.html <%split%> ICS 10 Topics": [1, 426, 0, 0.005695293118381279], "https://www.ics.uci.edu/~kay/courses/139w/graphicsactivity.html <%split%> Graphics Activity": [1, 461, 0, 0.005262895593124567], "https://www.ics.uci.edu/~kay/courses/141/w00.html <%split%> ICS 141 Course Reference * Winter 2000": [1, 1289, 0, 0.0018822303091004073], "https://www.ics.uci.edu/~keldefra/teaching/spring2013/uci_cs132/cs132_outline.htm <%split%> Course Outline": [1, 394, 0, 0.006157854996016307], "https://www.ics.uci.edu/~magda/Courses/ics156/Ch1_files/slide0020.htm <%split%> ICS 156: Networking Lab": [1, 79, 1, 0.030711327448486394], "https://www.ics.uci.edu/~magda/Courses/ics156/Ch4_files/outline.htm <%split%> None": [2, 1048, 0, 0.004630142878684017], "https://www.ics.uci.edu/~magda/Courses/ics156/Ch4_files/slide0006.htm <%split%> ICS 156: Networking Lab": [1, 58, 0, 0.04183094600742112], "https://www.ics.uci.edu/~magda/Courses/ics156/old_Lab_1.html <%split%> LABORATORY MANUAL ": [2, 3830, 1, 0.0012669424900419975], "https://www.ics.uci.edu/~magda/Courses/ics243B/outline.html <%split%> Course Outline": [1, 522, 0, 0.004647882889713458], "https://www.ics.uci.edu/~rohit/IEEE-L7-FTP-COLUMN-FINAL.htm <%split%> I Want My FTP: Bits on Demand": [45, 2196, 1, 0.04971710795963986], "https://www.ics.uci.edu/~rohit/IEEE-L7-Jon-NNTP.html <%split%> The News about Jon": [6, 3006, 1, 0.004842704328204441], "https://www.ics.uci.edu/~rohit/IEEE-L7-SMTP.html <%split%> The Spec's in the Mail": [10, 2748, 0, 0.008828947847272289], "https://www.ics.uci.edu/~rohit/L7-1.html <%split%> Life in a TP... [Seventh Heaven #1]": [9, 1481, 0, 0.01474392560153533], "https://www.ics.uci.edu/~thornton/ics32/Notes/Sockets/ <%split%> ICS 32 Winter 2019, Notes and Examples: Networks and Sockets": [1, 5003, 0, 0.00048494800488315515], "https://www.ics.uci.edu/~vitus/ics1c/doc/hw4a.html <%split%> ICS 1C HW 4 Submission Form": [1, 313, 1, 0.007751421304889537]}, "ftpclient": {"http://mondego.ics.uci.edu/projects/SourcererCC/precision/TP-2.txt <%split%> None": [2, 7476, 0, 0.0011459409750833852]}, "ftping": {"http://archive.ics.uci.edu/ml/donation_policy.html <%split%> UCI Machine Learning Repository: Donation Policy": [1, 415, 0, 0.010321752686413721]}, "ftpspace": {"https://www.ics.uci.edu/~ics1c/doc/spiders.html <%split%> New Spiders Roam the Web": [1, 1020, 0, 0.004199536632217347]}, "ftpsrv": {"https://www.ics.uci.edu/~rohit/IEEE-L7-FTP-COLUMN-FINAL.htm <%split%> I Want My FTP: Bits on Demand": [1, 2196, 1, 0.0019506044466583306]}, "ftpuser": {"https://www.ics.uci.edu/~magda/Courses/ics156/old_Lab_4.html <%split%> LABORATORY MANUAL ": [1, 1887, 0, 0.002270019801198566]}, "fts": {"http://sparcfire.ics.uci.edu/query/ <%split%> SpArcFiRe Web Interface": [1, 1205, 0, 0.0035547944936611567]}, "ftse": {"http://archive.ics.uci.edu/ml/datasets/ISTANBUL+STOCK+EXCHANGE <%split%> UCI Machine Learning Repository: ISTANBUL STOCK EXCHANGE Data Set": [1, 246, 0, 0.01741271286529144]}, "ftsearcherab": {"http://flamingo.ics.uci.edu/releases/2.0.1/src/filtertree/ <%split%> Index of /releases/2.0.1/src/filtertree": [1, 37, 0, 0.09473989498589325], "http://flamingo.ics.uci.edu/releases/2.0/src/filtertree/ <%split%> Index of /releases/2.0/src/filtertree": [1, 76, 0, 0.04612336992734276], "http://flamingo.ics.uci.edu/releases/2.0/src/filtertree/makefile <%split%> None": [5, 240, 0, 0.07302866905162604], "http://flamingo.ics.uci.edu/releases/3.0/src/filtertree/ <%split%> Index of /releases/3.0/src/filtertree": [1, 43, 0, 0.08152037475530349], "http://flamingo.ics.uci.edu/releases/4.0/src/filtertree/src/ <%split%> Index of /releases/4.0/src/filtertree/src": [1, 43, 0, 0.08152037475530349], "http://flamingo.ics.uci.edu/releases/4.0/src/filtertree/src/ftsearcherabs.cc <%split%> None": [1, 1, 0, 3.50537611447805]}, "ftsearchermem": {"http://flamingo.ics.uci.edu/releases/2.0.1/src/filtertree/ <%split%> Index of /releases/2.0.1/src/filtertree": [1, 37, 0, 0.08251563360766], "http://flamingo.ics.uci.edu/releases/2.0.1/src/filtertree/ftsearchermem.cc <%split%> None": [1, 1, 0, 3.05307844348342], "http://flamingo.ics.uci.edu/releases/2.0.1/src/filtertree/unittest.cc <%split%> None": [3, 510, 0, 0.017959284961667175], "http://flamingo.ics.uci.edu/releases/2.0.1/src/filtertree/wrappers/makefile <%split%> None": [1, 111, 0, 0.027505211202553333], "http://flamingo.ics.uci.edu/releases/2.0/src/filtertree/ <%split%> Index of /releases/2.0/src/filtertree": [1, 76, 0, 0.04017208478267657], "http://flamingo.ics.uci.edu/releases/2.0/src/filtertree/example.cc <%split%> None": [4, 554, 0, 0.02204388767858065], "http://flamingo.ics.uci.edu/releases/2.0/src/filtertree/makefile <%split%> None": [8, 240, 0, 0.10176928144944733], "http://flamingo.ics.uci.edu/releases/2.0/src/filtertree/perftest.cc <%split%> None": [2, 208, 0, 0.029356523495032885], "http://flamingo.ics.uci.edu/releases/3.0/src/filtertree/ <%split%> Index of /releases/3.0/src/filtertree": [1, 43, 0, 0.07100182426705627], "http://flamingo.ics.uci.edu/releases/3.0/src/filtertree/example.cc <%split%> None": [7, 1527, 0, 0.013995775444914172], "http://flamingo.ics.uci.edu/releases/3.0/src/filtertree/perftest.cc <%split%> None": [4, 1159, 0, 0.010536940270865987], "http://flamingo.ics.uci.edu/releases/3.0/src/filtertree/unittest.cc <%split%> None": [11, 3289, 0, 0.010210964693924482], "http://flamingo.ics.uci.edu/releases/4.0/src/filtertree/src/ <%split%> Index of /releases/4.0/src/filtertree/src": [1, 43, 0, 0.07100182426705627], "http://flamingo.ics.uci.edu/releases/4.0/src/filtertree/src/example.cc <%split%> None": [9, 2074, 0, 0.013248652840574146], "http://flamingo.ics.uci.edu/releases/4.0/src/filtertree/src/perftest.cc <%split%> None": [8, 1303, 0, 0.01874491753481762], "http://flamingo.ics.uci.edu/releases/4.1/src/filtertree/src/example.cc <%split%> None": [10, 2251, 0, 0.013563209433511417], "http://flamingo.ics.uci.edu/releases/4.1/src/filtertree/src/unittest.cc <%split%> None": [11, 3262, 0, 0.010295482182194242]}, "ftsearcherondisk": {"http://flamingo.ics.uci.edu/releases/3.0/src/filtertree/ <%split%> Index of /releases/3.0/src/filtertree": [1, 43, 0, 0.07861482274115697], "http://flamingo.ics.uci.edu/releases/3.0/src/filtertree/example.cc <%split%> None": [3, 1527, 0, 0.006641330801315815], "http://flamingo.ics.uci.edu/releases/3.0/src/filtertree/ftsearcherondisk.cc <%split%> None": [2, 34, 0, 0.19884925752174998], "http://flamingo.ics.uci.edu/releases/3.0/src/filtertree/perftest.cc <%split%> None": [4, 1159, 0, 0.011666738146228645], "http://flamingo.ics.uci.edu/releases/4.0/src/filtertree/src/ <%split%> Index of /releases/4.0/src/filtertree/src": [1, 43, 0, 0.07861482274115697], "http://flamingo.ics.uci.edu/releases/4.0/src/filtertree/src/example.cc <%split%> None": [3, 2074, 0, 0.00488973584069877], "http://flamingo.ics.uci.edu/releases/4.0/src/filtertree/src/perftest.cc <%split%> None": [1, 1303, 0, 0.002594349484167114], "http://flamingo.ics.uci.edu/releases/4.1/src/filtertree/src/example.cc <%split%> None": [3, 2251, 0, 0.004505247504935251]}, "ftsj": {"https://cbcl.ics.uci.edu/public_data/shilab/RNAseq_elmira_09072016/MAJIQ/MAJIQ-DELTAPSI/voila_dpsi_293twt_cfim59ko/ <%split%> MAJIQ LSV \u0394\u03a8 Summary": [1, 5740, 0, 0.0005582484527550642], "https://cbcl.ics.uci.edu/public_data/shilab/RNAseq_elmira_09072016/MAJIQ/MAJIQ-DELTAPSI/voila_dpsi_293twt_cfim59ko/summaries/14_293TWT_CFIM59KO.deltapsi_quantify_deltapsi.html <%split%> LSV \u0394\u03a8 Gene Summary": [1, 732, 1, 0.004377522020237799], "https://cbcl.ics.uci.edu/public_data/shilab/RNAseq_elmira_09072016/MAJIQ/MAJIQ-DELTAPSI/voila_dpsi_293twt_cfim68ko/ <%split%> MAJIQ LSV \u0394\u03a8 Summary": [1, 5725, 0, 0.0005597111124566059], "https://cbcl.ics.uci.edu/public_data/shilab/RNAseq_elmira_09072016/MAJIQ/MAJIQ-DELTAPSI/voila_dpsi_293twt_cfim68ko/summaries/16_293TWT_CFIM68KO.deltapsi_quantify_deltapsi.html <%split%> LSV \u0394\u03a8 Gene Summary": [1, 733, 1, 0.0043715499574543916], "https://cbcl.ics.uci.edu/public_data/shilab/RNAseq_elmira_09072016/MAJIQ/MAJIQ-DELTAPSI/voila_dpsi_293wt_cfim59ko/ <%split%> MAJIQ LSV \u0394\u03a8 Summary": [1, 1943, 0, 0.001649174533615064], "https://cbcl.ics.uci.edu/public_data/shilab/RNAseq_elmira_09072016/MAJIQ/MAJIQ-DELTAPSI/voila_dpsi_293wt_cfim68ko/ <%split%> MAJIQ LSV \u0394\u03a8 Summary": [1, 3316, 0, 0.0009663287451188386], "https://cbcl.ics.uci.edu/public_data/shilab/RNAseq_elmira_09072016/MAJIQ/MAJIQ-DELTAPSI/voila_dpsi_293wt_cstf64tko/ <%split%> MAJIQ LSV \u0394\u03a8 Summary": [1, 946, 0, 0.003387258053714661], "https://cbcl.ics.uci.edu/public_data/shilab/RNAseq_elmira_09072016/MAJIQ/MAJIQ-DELTAPSI/voila_dpsi_293wt_cstf64tko/summaries/0_293WT_CSTF64TKO.deltapsi_quantify_deltapsi.html <%split%> LSV \u0394\u03a8 Gene Summary": [1, 732, 1, 0.004377522020237799], "https://cbcl.ics.uci.edu/public_data/shilab/forColleen/MAJIQ/voila-KO-cort/ <%split%> MAJIQ LSV \u0394\u03a8 Summary": [2, 44533, 0, 0.00014390883698893266], "https://cbcl.ics.uci.edu/public_data/shilab/forColleen/MAJIQ/voila-KO-hind/ <%split%> MAJIQ LSV \u0394\u03a8 Summary": [4, 215444, 0, 5.949288202621691e-05], "https://cbcl.ics.uci.edu/public_data/shilab/forColleen/MAJIQ/voila-Wt-cort/ <%split%> MAJIQ LSV \u0394\u03a8 Summary": [2, 185124, 0, 3.461837599462057e-05], "https://cbcl.ics.uci.edu/public_data/shilab/forColleen/MAJIQ/voila-Wt-hind/ <%split%> MAJIQ LSV \u0394\u03a8 Summary": [2, 212660, 0, 3.0135861175717758e-05]}, "ftsjd": {"https://cbcl.ics.uci.edu/public_data/shilab/forColleen/MAJIQ/voila-KO-cort/ <%split%> MAJIQ LSV \u0394\u03a8 Summary": [8, 44533, 0, 0.0006613463945449408], "https://cbcl.ics.uci.edu/public_data/shilab/forColleen/MAJIQ/voila-KO-hind/ <%split%> MAJIQ LSV \u0394\u03a8 Summary": [8, 215444, 0, 0.0001367025258919712], "https://cbcl.ics.uci.edu/public_data/shilab/forColleen/MAJIQ/voila-Wt-cort/ <%split%> MAJIQ LSV \u0394\u03a8 Summary": [8, 185124, 0, 0.00015909195451843007], "https://cbcl.ics.uci.edu/public_data/shilab/forColleen/MAJIQ/voila-Wt-hind/ <%split%> MAJIQ LSV \u0394\u03a8 Summary": [6, 212660, 0, 0.00010386910674881212]}, "ftsolo": {"https://www.ics.uci.edu/~arcadia/Teamware/docs/AllNames.html <%split%> \n  Index of all Fields and Methods\n": [2, 3718, 1, 0.0021422793809562734], "https://www.ics.uci.edu/~arcadia/Teamware/docs/Foundation.Objv.MetaClass.html <%split%> \n  Class Foundation.Objv.MetaClass\n": [3, 550, 1, 0.021722712922896615]}, "ftsoloadd": {"https://www.ics.uci.edu/~arcadia/Teamware/docs/AllNames.html <%split%> \n  Index of all Fields and Methods\n": [2, 3718, 1, 0.0021422793809562734], "https://www.ics.uci.edu/~arcadia/Teamware/docs/Foundation.Objv.MetaClass.html <%split%> \n  Class Foundation.Objv.MetaClass\n": [3, 550, 1, 0.021722712922896615]}, "ftsoloaddlist": {"https://www.ics.uci.edu/~arcadia/Teamware/docs/AllNames.html <%split%> \n  Index of all Fields and Methods\n": [2, 3718, 1, 0.0021422793809562734], "https://www.ics.uci.edu/~arcadia/Teamware/docs/Foundation.Objv.MetaClass.html <%split%> \n  Class Foundation.Objv.MetaClass\n": [3, 550, 1, 0.021722712922896615]}, "ftsoloremove": {"https://www.ics.uci.edu/~arcadia/Teamware/docs/AllNames.html <%split%> \n  Index of all Fields and Methods\n": [2, 3718, 1, 0.0021422793809562734], "https://www.ics.uci.edu/~arcadia/Teamware/docs/Foundation.Objv.MetaClass.html <%split%> \n  Class Foundation.Objv.MetaClass\n": [3, 550, 1, 0.021722712922896615]}, "ftsoloremovelist": {"https://www.ics.uci.edu/~arcadia/Teamware/docs/AllNames.html <%split%> \n  Index of all Fields and Methods\n": [2, 3718, 1, 0.0021422793809562734], "https://www.ics.uci.edu/~arcadia/Teamware/docs/Foundation.Objv.MetaClass.html <%split%> \n  Class Foundation.Objv.MetaClass\n": [3, 550, 1, 0.021722712922896615]}, "fttp": {"https://www.ics.uci.edu/~ics1c/doc/www_faq.html <%split%> World Wide Web FAQ": [1, 12601, 0, 0.0003399355102659864]}, "ftype": {"https://www.ics.uci.edu/~chenli/pods05/sig-alternate.cls <%split%> None": [1, 1862, 0, 0.0023004980477237882]}}