{"kg": {"https://www.ics.uci.edu/~kay/courses/31/hw/lab1.html <%split%> ICS 31 Lab 1": [1, 2726, 0, 0.0014609308030805988], "https://www.ics.uci.edu/~kay/courses/31/hw/lab2.html <%split%> ICS 31 Lab 2": [2, 3479, 0, 0.002289449479274339]}, "kgal": {"https://www.ics.uci.edu/~kkask/Spring-2018%20CS273P/Demos/Intro_Tutorial.ipynb <%split%> None": [1, 2148, 0, 0.00199419337284064]}, "kgane": {"http://archive.ics.uci.edu/ml/datasets/Opinosis+Opinion+%26frasl%3B+Review <%split%> UCI Machine Learning Repository: Opinosis Opinion \u2044 Review Data Set": [1, 235, 0, 0.01822777602068806]}, "kgb": {"https://www.ics.uci.edu/~dan/class/267P/datasets/calgary/news <%split%> None": [1, 42135, 0, 0.00010166197614481296]}, "kgce": {"https://www.ics.uci.edu/~kkask/Spring-2018%20CS273P/Demos/Intro_Tutorial.ipynb <%split%> None": [1, 2148, 0, 0.00199419337284064]}, "kgntre": {"https://www.ics.uci.edu/~kkask/Spring-2018%20CS273P/Demos/Intro_Tutorial.ipynb <%split%> None": [1, 2148, 0, 0.00199419337284064]}, "kgon": {"https://www.ics.uci.edu/~eppstein/bibs/eppstein.html <%split%> BibTeX: David Eppstein": [1, 14330, 0, 0.0002779132846613896], "https://www.ics.uci.edu/~eppstein/pubs/pubs.ff <%split%> David Eppstein - Publications": [1, 36547, 0, 0.00010896920045961945]}, "kgp": {"https://ngs.ics.uci.edu/iit-students/ <%split%> IIT Students  \u2013 Ramesh Jain": [1, 337, 0, 0.012710763693951615]}, "kgvvlww": {"https://www.ics.uci.edu/~kay/courses/10/hw/hw7-lists.xml <%split%> None": [1, 172, 0, 0.024904228865474966]}}