{"lz": {"https://www.ics.uci.edu/~dan/class/267P/datasets/calgary/news <%split%> None": [1, 42135, 0, 0.00010166197614481296]}, "lzfg": {"https://www.ics.uci.edu/~dan/class/267P/refs.html <%split%>  CompSci 267: Data Compression\n": [1, 546, 0, 0.007845288214032407]}, "lzss": {"https://www.ics.uci.edu/~dan/class/267P/refs.html <%split%>  CompSci 267: Data Compression\n": [1, 546, 0, 0.007845288214032407]}, "lztfl": {"https://cbcl.ics.uci.edu/public_data/shilab/forColleen/MAJIQ/voila-KO-cort/ <%split%> MAJIQ LSV \u0394\u03a8 Summary": [14, 44533, 0, 0.0011573561904536466], "https://cbcl.ics.uci.edu/public_data/shilab/forColleen/MAJIQ/voila-KO-hind/ <%split%> MAJIQ LSV \u0394\u03a8 Summary": [14, 215444, 0, 0.00023922942031094966], "https://cbcl.ics.uci.edu/public_data/shilab/forColleen/MAJIQ/voila-Wt-cort/ <%split%> MAJIQ LSV \u0394\u03a8 Summary": [10, 185124, 0, 0.0001988649431480376], "https://cbcl.ics.uci.edu/public_data/shilab/forColleen/MAJIQ/voila-Wt-hind/ <%split%> MAJIQ LSV \u0394\u03a8 Summary": [8, 212660, 0, 0.0001384921423317495]}, "lztr": {"https://cbcl.ics.uci.edu/public_data/shilab/forColleen/MAJIQ/voila-KO-cort/ <%split%> MAJIQ LSV \u0394\u03a8 Summary": [8, 44533, 0, 0.0006613463945449408], "https://cbcl.ics.uci.edu/public_data/shilab/forColleen/MAJIQ/voila-KO-hind/ <%split%> MAJIQ LSV \u0394\u03a8 Summary": [6, 215444, 0, 0.00010252689441897843], "https://cbcl.ics.uci.edu/public_data/shilab/forColleen/MAJIQ/voila-Wt-cort/ <%split%> MAJIQ LSV \u0394\u03a8 Summary": [8, 185124, 0, 0.00015909195451843007], "https://cbcl.ics.uci.edu/public_data/shilab/forColleen/MAJIQ/voila-Wt-hind/ <%split%> MAJIQ LSV \u0394\u03a8 Summary": [8, 212660, 0, 0.0001384921423317495]}, "lzumuqjogsrj": {"https://www.ics.uci.edu/~kkask/Spring-2018%20CS273P/Demos/Intro_Tutorial.ipynb <%split%> None": [1, 2148, 0, 0.00199419337284064]}, "lzw": {"https://www.ics.uci.edu/~dan/class/267P/refs.html <%split%>  CompSci 267: Data Compression\n": [1, 546, 0, 0.006971439762164892], "https://www.ics.uci.edu/~kay/courses/10a/hw/hw6.html <%split%> ICS 10A Assignment 6 * Fall 2003": [1, 1750, 0, 0.0021750892057954465], "https://www.ics.uci.edu/~theory/269/070309.html <%split%> Theory Seminar, Mar 9, 2007": [2, 111, 0, 0.06858389387643299]}}