{"wx": {"https://www.ics.uci.edu/~majumder/VC/211HW3/vlfeat/doc/matlab/vl_dwaffine.html <%split%> VLFeat - Documentation > MATLAB API > IMOP - vl_dwaffine": [1, 130, 0, 0.03295021049893611]}, "wxample": {"https://ngs.ics.uci.edu/author/ramesh/page/129/ <%split%> Ramesh \u2013 Page 129 \u2013 Ramesh Jain": [1, 322, 0, 0.011821136988018729], "https://ngs.ics.uci.edu/category/entrepreneurism/page/14/ <%split%> Entrepreneurism \u2013 Page 14 \u2013 Ramesh Jain": [1, 317, 0, 0.012007590252813978], "https://ngs.ics.uci.edu/friendster-and-youtube-or-myspace/ <%split%> Friendster and (Youtube OR Myspace) \u2013 Ramesh Jain": [1, 299, 0, 0.012730455217866324]}, "wxebt": {"https://www.ics.uci.edu/~kkask/Spring-2018%20CS273P/Demos/Intro_Tutorial.ipynb <%split%> None": [1, 2148, 0, 0.00199419337284064]}, "wxtnzbae": {"https://www.ics.uci.edu/~kay/courses/10/hw/hw7-lists.xml <%split%> None": [1, 172, 0, 0.024904228865474966]}, "wxwxw": {"https://www.ics.uci.edu/~eppstein/cgt/chomp.html <%split%> ": [3, 1460, 0, 0.008801768557934986]}, "wxyz": {"https://www.ics.uci.edu/~pattis/ICS-33/lectures/review.txt <%split%> None": [1, 10498, 0, 0.0004080327076454272]}}